{
  "asof": "2026-02-19",
  "horizon_bdays": 42,
  "p_any": 0.6132371224372666,
  "p_components": {
    "p_dd_2m": 0.30459196339469347,
    "p_crash_1d": 0.19938431011241725,
    "p_crash_30d": 0.30532610238577784
  },
  "score": 61.32371224372666,
  "pre_alert": false,
  "crisis_confirmed": false,
  "gate_status": {
    "passed": false,
    "reasons": [],
    "signals": {
      "HY_OAS_CHG_20D_POS": {
        "z": 0.8076875586892361,
        "thr": 0.16328903989663135
      },
      "IG_OAS_CHG_20D_POS": {
        "z": 0.7086076111901813,
        "thr": 0.13974536678746438
      },
      "HY_IG_CHG_20D_POS": {
        "z": 0.7714308298926498,
        "thr": 0.23470565496162527
      },
      "VIX_CHG_5D_POS": {
        "z": -0.1581338592230887,
        "thr": 0.2499065124592313
      },
      "NFCI_CHG_4W_POS": {
        "z": -0.014362021096957193,
        "thr": 0.09105531025620572
      },
      "STLFSI4_CHG_4W_POS": {
        "z": 0.08330106813387243,
        "thr": 0.27598483281705466
      },
      "SPX_MDD_1M": {
        "z": -0.6366429760519225,
        "thr": 0.08977053215700995
      },
      "SPX_RVOL_1M": {
        "z": -0.5012977561949854,
        "thr": 0.007271680613707311
      },
      "SPX_RET_20D_NEG": {
        "z": 0.4726764991881832,
        "thr": 0.5440621822297007
      }
    }
  },
  "coverage": 1.0,
  "regime_confidence": "high",
  "regime": "平常",
  "thresholds": {
    "notice_p": 0.6353911388864543,
    "alert_p": 0.6511303933499315,
    "pre_alert_p": 0.6511313933499315,
    "gate_percentile": 0.8,
    "gate_thresholds": {
      "HY_OAS_CHG_20D_POS": 0.16328903989663135,
      "IG_OAS_CHG_20D_POS": 0.13974536678746438,
      "HY_IG_CHG_20D_POS": 0.23470565496162527,
      "VIX_CHG_5D_POS": 0.2499065124592313,
      "NFCI_CHG_4W_POS": 0.09105531025620572,
      "STLFSI4_CHG_4W_POS": 0.27598483281705466,
      "SPX_MDD_1M": 0.08977053215700995,
      "SPX_RVOL_1M": 0.007271680613707311,
      "SPX_RET_20D_NEG": 0.5440621822297007
    },
    "targets": {
      "pre_alert_recall_min_dd_2m": 0.6,
      "crisis_precision_min_dd_2m": 0.6
    }
  },
  "data_staleness": {
    "WEI": {
      "fred_id": "WEI",
      "freq_group": "weekly",
      "last_obs_date": "2026-02-07",
      "stale_days": 12,
      "stale": false
    },
    "ICSA": {
      "fred_id": "ICSA",
      "freq_group": "weekly",
      "last_obs_date": "2026-02-07",
      "stale_days": 12,
      "stale": false
    },
    "CCSA": {
      "fred_id": "CCSA",
      "freq_group": "weekly",
      "last_obs_date": "2026-01-31",
      "stale_days": 19,
      "stale": false
    },
    "T10Y3M": {
      "fred_id": "T10Y3M",
      "freq_group": "daily",
      "last_obs_date": "2026-02-18",
      "stale_days": 1,
      "stale": false
    },
    "HY_OAS": {
      "fred_id": "BAMLH0A0HYM2",
      "freq_group": "daily",
      "last_obs_date": "2026-02-17",
      "stale_days": 2,
      "stale": false
    },
    "IG_OAS": {
      "fred_id": "BAMLC0A0CM",
      "freq_group": "daily",
      "last_obs_date": "2026-02-17",
      "stale_days": 2,
      "stale": false
    },
    "NFCI": {
      "fred_id": "NFCI",
      "freq_group": "weekly",
      "last_obs_date": "2026-02-06",
      "stale_days": 13,
      "stale": false
    },
    "STLFSI4": {
      "fred_id": "STLFSI4",
      "freq_group": "weekly",
      "last_obs_date": "2026-02-13",
      "stale_days": 6,
      "stale": false
    },
    "VIX": {
      "fred_id": "VIXCLS",
      "freq_group": "daily",
      "last_obs_date": "2026-02-17",
      "stale_days": 2,
      "stale": false
    },
    "SP500": {
      "fred_id": "SP500",
      "freq_group": "daily",
      "last_obs_date": "2026-02-17",
      "stale_days": 2,
      "stale": false
    },
    "FEDFUNDS_REF": {
      "fred_id": "FEDFUNDS",
      "freq_group": "monthly",
      "last_obs_date": "2026-01-01",
      "stale_days": 49,
      "stale": false
    },
    "UNRATE_REF": {
      "fred_id": "UNRATE",
      "freq_group": "monthly",
      "last_obs_date": "2026-01-01",
      "stale_days": 49,
      "stale": false
    }
  },
  "reference_only": {
    "FEDFUNDS_REF": 3.64,
    "UNRATE_REF": 4.3
  },
  "definitions": {
    "regimes": [
      "平常",
      "注意",
      "警戒",
      "早期警戒",
      "危機"
    ],
    "events": {
      "crash_1d_fwd": "42営業日以内に(任意のuで)1日先リターン<=-10%",
      "crash_30d_fwd": "42営業日以内に(任意のuで)30営業日先リターン<=-20%",
      "dd_2m": "42営業日以内に直近252営業日高値から-15%到達"
    },
    "stale_policy_A": {
      "daily": 7,
      "weekly": 21,
      "monthly": 120,
      "quarterly": 220
    },
    "split": {
      "mode": "adaptive",
      "train_end": "2022-09-26",
      "val_end": "2024-04-08",
      "test_start": "2024-04-09",
      "preferred_fixed": {
        "train_end": "2013-12-31",
        "val_end": "2018-12-31",
        "test_start": "2019-01-01"
      },
      "min_sizes": {
        "train": 1200,
        "val": 400,
        "test": 400
      }
    },
    "note": "3モデル（dd / 1日-10 / 30日-20）を個別学習し、p_any=1-Π(1-p)で合成。危機は「早期警戒 AND ゲート」確定。月次は参考表示のみ。週次はD→B整列。"
  },
  "backtest": {
    "windows": {
      "train_start": "2016-10-10",
      "train_end": "2022-09-26",
      "val_start": "2022-09-27",
      "val_end": "2024-04-08",
      "test_start": "2024-04-09",
      "test_end": "2026-02-19",
      "last_label_date": "2026-02-19"
    },
    "model_train_stats": {
      "p_dd_2m": {
        "train_pos_rate": 0.18316195372750643,
        "pos_weight": 4.459649122807018,
        "train_loss_best": 0.776154362294343,
        "epochs": 900,
        "l2": 1.0,
        "lr": 0.05,
        "batch": 4096
      },
      "p_crash_1d": {
        "train_pos_rate": 0.02699228791773779,
        "pos_weight": 12.0,
        "train_loss_best": 0.554000180681428,
        "epochs": 900,
        "l2": 1.0,
        "lr": 0.05,
        "batch": 4096
      },
      "p_crash_30d": {
        "train_pos_rate": 0.037275064267352186,
        "pos_weight": 12.0,
        "train_loss_best": 0.7244713115835247,
        "epochs": 900,
        "l2": 1.0,
        "lr": 0.05,
        "batch": 4096
      }
    },
    "picked_pre_alert_info": {
      "thr": 0.6511313933499315,
      "q": 0.74,
      "cm_dd_2m": {
        "tp": 74,
        "fp": 30,
        "fn": 48,
        "tn": 248,
        "precision": 0.7115384615384616,
        "recall": 0.6065573770491803
      },
      "pre_days": 104,
      "recall_min": 0.6
    },
    "picked_gate_info": {
      "thresholds": {
        "HY_OAS_CHG_20D_POS": 0.16328903989663135,
        "IG_OAS_CHG_20D_POS": 0.13974536678746438,
        "HY_IG_CHG_20D_POS": 0.23470565496162527,
        "VIX_CHG_5D_POS": 0.2499065124592313,
        "NFCI_CHG_4W_POS": 0.09105531025620572,
        "STLFSI4_CHG_4W_POS": 0.27598483281705466,
        "SPX_MDD_1M": 0.08977053215700995,
        "SPX_RVOL_1M": 0.007271680613707311,
        "SPX_RET_20D_NEG": 0.5440621822297007
      },
      "cm_dd_2m": {
        "tp": 41,
        "fp": 19,
        "fn": 81,
        "tn": 259,
        "precision": 0.6833333333333333,
        "recall": 0.3360655737704918
      },
      "precision_min": 0.6,
      "chosen_recall": 0.3360655737704918
    },
    "metrics_val_two_stage": {
      "days": 400,
      "crisis_days": 60,
      "crisis_share": 0.15,
      "base_dd_2m": 0.305,
      "base_crash_1d_fwd": 0.0,
      "base_crash_30d_fwd": 0.0,
      "hit_dd_2m": 0.6833333333333333,
      "lift_dd_2m": 2.2404371584699456,
      "cm_dd_2m": {
        "tp": 41,
        "fp": 19,
        "fn": 81,
        "tn": 259,
        "precision": 0.6833333333333333,
        "recall": 0.3360655737704918
      },
      "hit_crash_1d_fwd": 0.0,
      "lift_crash_1d_fwd": null,
      "cm_crash_1d_fwd": {
        "tp": 0,
        "fp": 60,
        "fn": 0,
        "tn": 340,
        "precision": 0.0,
        "recall": null
      },
      "hit_crash_30d_fwd": 0.0,
      "lift_crash_30d_fwd": null,
      "cm_crash_30d_fwd": {
        "tp": 0,
        "fp": 60,
        "fn": 0,
        "tn": 340,
        "precision": 0.0,
        "recall": null
      }
    },
    "metrics_test_two_stage": {
      "days": 488,
      "crisis_days": 53,
      "crisis_share": 0.10860655737704918,
      "base_dd_2m": 0.10860655737704918,
      "base_crash_1d_fwd": 0.0,
      "base_crash_30d_fwd": 0.0,
      "hit_dd_2m": 0.6415094339622641,
      "lift_dd_2m": 5.906728373086508,
      "cm_dd_2m": {
        "tp": 34,
        "fp": 19,
        "fn": 19,
        "tn": 416,
        "precision": 0.6415094339622641,
        "recall": 0.6415094339622641
      },
      "hit_crash_1d_fwd": 0.0,
      "lift_crash_1d_fwd": null,
      "cm_crash_1d_fwd": {
        "tp": 0,
        "fp": 53,
        "fn": 0,
        "tn": 435,
        "precision": 0.0,
        "recall": null
      },
      "hit_crash_30d_fwd": 0.0,
      "lift_crash_30d_fwd": null,
      "cm_crash_30d_fwd": {
        "tp": 0,
        "fp": 53,
        "fn": 0,
        "tn": 435,
        "precision": 0.0,
        "recall": null
      }
    },
    "by_regime_test": {
      "平常": {
        "days": 420,
        "rate_dd_2m": 0.03333333333333333,
        "rate_crash_1d_fwd": 0.0,
        "rate_crash_30d_fwd": 0.0,
        "avg_p_any": 0.5485025963955886
      },
      "注意": {
        "days": 15,
        "rate_dd_2m": 0.3333333333333333,
        "rate_crash_1d_fwd": 0.0,
        "rate_crash_30d_fwd": 0.0,
        "avg_p_any": 0.644146239238058
      },
      "警戒": {
        "days": 0
      },
      "早期警戒": {
        "days": 0
      },
      "危機": {
        "days": 53,
        "rate_dd_2m": 0.6415094339622641,
        "rate_crash_1d_fwd": 0.0,
        "rate_crash_30d_fwd": 0.0,
        "avg_p_any": 0.7632584051534139
      }
    },
    "threshold_scan_val": [
      {
        "threshold": 0.6813419794393225,
        "days": 400,
        "crisis_days": 80,
        "crisis_share": 0.2,
        "base_dd_2m": 0.305,
        "base_crash_1d_fwd": 0.0,
        "base_crash_30d_fwd": 0.0,
        "hit_dd_2m": 0.75,
        "lift_dd_2m": 2.459016393442623,
        "cm_dd_2m": {
          "tp": 60,
          "fp": 20,
          "fn": 62,
          "tn": 258,
          "precision": 0.75,
          "recall": 0.4918032786885246
        },
        "hit_crash_1d_fwd": 0.0,
        "lift_crash_1d_fwd": null,
        "cm_crash_1d_fwd": {
          "tp": 0,
          "fp": 80,
          "fn": 0,
          "tn": 320,
          "precision": 0.0,
          "recall": null
        },
        "hit_crash_30d_fwd": 0.0,
        "lift_crash_30d_fwd": null,
        "cm_crash_30d_fwd": {
          "tp": 0,
          "fp": 80,
          "fn": 0,
          "tn": 320,
          "precision": 0.0,
          "recall": null
        },
        "percentile": 0.8
      },
      {
        "threshold": 0.7095576253873425,
        "days": 400,
        "crisis_days": 60,
        "crisis_share": 0.15,
        "base_dd_2m": 0.305,
        "base_crash_1d_fwd": 0.0,
        "base_crash_30d_fwd": 0.0,
        "hit_dd_2m": 0.75,
        "lift_dd_2m": 2.459016393442623,
        "cm_dd_2m": {
          "tp": 45,
          "fp": 15,
          "fn": 77,
          "tn": 263,
          "precision": 0.75,
          "recall": 0.36885245901639346
        },
        "hit_crash_1d_fwd": 0.0,
        "lift_crash_1d_fwd": null,
        "cm_crash_1d_fwd": {
          "tp": 0,
          "fp": 60,
          "fn": 0,
          "tn": 340,
          "precision": 0.0,
          "recall": null
        },
        "hit_crash_30d_fwd": 0.0,
        "lift_crash_30d_fwd": null,
        "cm_crash_30d_fwd": {
          "tp": 0,
          "fp": 60,
          "fn": 0,
          "tn": 340,
          "precision": 0.0,
          "recall": null
        },
        "percentile": 0.85
      },
      {
        "threshold": 0.7366568456135273,
        "days": 400,
        "crisis_days": 40,
        "crisis_share": 0.1,
        "base_dd_2m": 0.305,
        "base_crash_1d_fwd": 0.0,
        "base_crash_30d_fwd": 0.0,
        "hit_dd_2m": 0.675,
        "lift_dd_2m": 2.2131147540983607,
        "cm_dd_2m": {
          "tp": 27,
          "fp": 13,
          "fn": 95,
          "tn": 265,
          "precision": 0.675,
          "recall": 0.22131147540983606
        },
        "hit_crash_1d_fwd": 0.0,
        "lift_crash_1d_fwd": null,
        "cm_crash_1d_fwd": {
          "tp": 0,
          "fp": 40,
          "fn": 0,
          "tn": 360,
          "precision": 0.0,
          "recall": null
        },
        "hit_crash_30d_fwd": 0.0,
        "lift_crash_30d_fwd": null,
        "cm_crash_30d_fwd": {
          "tp": 0,
          "fp": 40,
          "fn": 0,
          "tn": 360,
          "precision": 0.0,
          "recall": null
        },
        "percentile": 0.9
      },
      {
        "threshold": 0.7513944440187423,
        "days": 400,
        "crisis_days": 32,
        "crisis_share": 0.08,
        "base_dd_2m": 0.305,
        "base_crash_1d_fwd": 0.0,
        "base_crash_30d_fwd": 0.0,
        "hit_dd_2m": 0.71875,
        "lift_dd_2m": 2.3565573770491803,
        "cm_dd_2m": {
          "tp": 23,
          "fp": 9,
          "fn": 99,
          "tn": 269,
          "precision": 0.71875,
          "recall": 0.1885245901639344
        },
        "hit_crash_1d_fwd": 0.0,
        "lift_crash_1d_fwd": null,
        "cm_crash_1d_fwd": {
          "tp": 0,
          "fp": 32,
          "fn": 0,
          "tn": 368,
          "precision": 0.0,
          "recall": null
        },
        "hit_crash_30d_fwd": 0.0,
        "lift_crash_30d_fwd": null,
        "cm_crash_30d_fwd": {
          "tp": 0,
          "fp": 32,
          "fn": 0,
          "tn": 368,
          "precision": 0.0,
          "recall": null
        },
        "percentile": 0.92
      },
      {
        "threshold": 0.7622697009874336,
        "days": 400,
        "crisis_days": 24,
        "crisis_share": 0.06,
        "base_dd_2m": 0.305,
        "base_crash_1d_fwd": 0.0,
        "base_crash_30d_fwd": 0.0,
        "hit_dd_2m": 0.7916666666666666,
        "lift_dd_2m": 2.5956284153005464,
        "cm_dd_2m": {
          "tp": 19,
          "fp": 5,
          "fn": 103,
          "tn": 273,
          "precision": 0.7916666666666666,
          "recall": 0.1557377049180328
        },
        "hit_crash_1d_fwd": 0.0,
        "lift_crash_1d_fwd": null,
        "cm_crash_1d_fwd": {
          "tp": 0,
          "fp": 24,
          "fn": 0,
          "tn": 376,
          "precision": 0.0,
          "recall": null
        },
        "hit_crash_30d_fwd": 0.0,
        "lift_crash_30d_fwd": null,
        "cm_crash_30d_fwd": {
          "tp": 0,
          "fp": 24,
          "fn": 0,
          "tn": 376,
          "precision": 0.0,
          "recall": null
        },
        "percentile": 0.94
      },
      {
        "threshold": 0.7771197850542548,
        "days": 400,
        "crisis_days": 16,
        "crisis_share": 0.04,
        "base_dd_2m": 0.305,
        "base_crash_1d_fwd": 0.0,
        "base_crash_30d_fwd": 0.0,
        "hit_dd_2m": 0.75,
        "lift_dd_2m": 2.459016393442623,
        "cm_dd_2m": {
          "tp": 12,
          "fp": 4,
          "fn": 110,
          "tn": 274,
          "precision": 0.75,
          "recall": 0.09836065573770492
        },
        "hit_crash_1d_fwd": 0.0,
        "lift_crash_1d_fwd": null,
        "cm_crash_1d_fwd": {
          "tp": 0,
          "fp": 16,
          "fn": 0,
          "tn": 384,
          "precision": 0.0,
          "recall": null
        },
        "hit_crash_30d_fwd": 0.0,
        "lift_crash_30d_fwd": null,
        "cm_crash_30d_fwd": {
          "tp": 0,
          "fp": 16,
          "fn": 0,
          "tn": 384,
          "precision": 0.0,
          "recall": null
        },
        "percentile": 0.96
      },
      {
        "threshold": 0.7989204027621719,
        "days": 400,
        "crisis_days": 8,
        "crisis_share": 0.02,
        "base_dd_2m": 0.305,
        "base_crash_1d_fwd": 0.0,
        "base_crash_30d_fwd": 0.0,
        "hit_dd_2m": 1.0,
        "lift_dd_2m": 3.278688524590164,
        "cm_dd_2m": {
          "tp": 8,
          "fp": 0,
          "fn": 114,
          "tn": 278,
          "precision": 1.0,
          "recall": 0.06557377049180328
        },
        "hit_crash_1d_fwd": 0.0,
        "lift_crash_1d_fwd": null,
        "cm_crash_1d_fwd": {
          "tp": 0,
          "fp": 8,
          "fn": 0,
          "tn": 392,
          "precision": 0.0,
          "recall": null
        },
        "hit_crash_30d_fwd": 0.0,
        "lift_crash_30d_fwd": null,
        "cm_crash_30d_fwd": {
          "tp": 0,
          "fp": 8,
          "fn": 0,
          "tn": 392,
          "precision": 0.0,
          "recall": null
        },
        "percentile": 0.98
      }
    ],
    "threshold_scan_test": [
      {
        "threshold": 0.6124634871635672,
        "days": 488,
        "crisis_days": 98,
        "crisis_share": 0.20081967213114754,
        "base_dd_2m": 0.10860655737704918,
        "base_crash_1d_fwd": 0.0,
        "base_crash_30d_fwd": 0.0,
        "hit_dd_2m": 0.41836734693877553,
        "lift_dd_2m": 3.852137081247594,
        "cm_dd_2m": {
          "tp": 41,
          "fp": 57,
          "fn": 12,
          "tn": 378,
          "precision": 0.41836734693877553,
          "recall": 0.7735849056603774
        },
        "hit_crash_1d_fwd": 0.0,
        "lift_crash_1d_fwd": null,
        "cm_crash_1d_fwd": {
          "tp": 0,
          "fp": 98,
          "fn": 0,
          "tn": 390,
          "precision": 0.0,
          "recall": null
        },
        "hit_crash_30d_fwd": 0.0,
        "lift_crash_30d_fwd": null,
        "cm_crash_30d_fwd": {
          "tp": 0,
          "fp": 98,
          "fn": 0,
          "tn": 390,
          "precision": 0.0,
          "recall": null
        },
        "percentile": 0.8
      },
      {
        "threshold": 0.6270465344080879,
        "days": 488,
        "crisis_days": 74,
        "crisis_share": 0.15163934426229508,
        "base_dd_2m": 0.10860655737704918,
        "base_crash_1d_fwd": 0.0,
        "base_crash_30d_fwd": 0.0,
        "hit_dd_2m": 0.5405405405405406,
        "lift_dd_2m": 4.977052524222336,
        "cm_dd_2m": {
          "tp": 40,
          "fp": 34,
          "fn": 13,
          "tn": 401,
          "precision": 0.5405405405405406,
          "recall": 0.7547169811320755
        },
        "hit_crash_1d_fwd": 0.0,
        "lift_crash_1d_fwd": null,
        "cm_crash_1d_fwd": {
          "tp": 0,
          "fp": 74,
          "fn": 0,
          "tn": 414,
          "precision": 0.0,
          "recall": null
        },
        "hit_crash_30d_fwd": 0.0,
        "lift_crash_30d_fwd": null,
        "cm_crash_30d_fwd": {
          "tp": 0,
          "fp": 74,
          "fn": 0,
          "tn": 414,
          "precision": 0.0,
          "recall": null
        },
        "percentile": 0.85
      },
      {
        "threshold": 0.6656730094473614,
        "days": 488,
        "crisis_days": 49,
        "crisis_share": 0.10040983606557377,
        "base_dd_2m": 0.10860655737704918,
        "base_crash_1d_fwd": 0.0,
        "base_crash_30d_fwd": 0.0,
        "hit_dd_2m": 0.6326530612244898,
        "lift_dd_2m": 5.8251829033500195,
        "cm_dd_2m": {
          "tp": 31,
          "fp": 18,
          "fn": 22,
          "tn": 417,
          "precision": 0.6326530612244898,
          "recall": 0.5849056603773585
        },
        "hit_crash_1d_fwd": 0.0,
        "lift_crash_1d_fwd": null,
        "cm_crash_1d_fwd": {
          "tp": 0,
          "fp": 49,
          "fn": 0,
          "tn": 439,
          "precision": 0.0,
          "recall": null
        },
        "hit_crash_30d_fwd": 0.0,
        "lift_crash_30d_fwd": null,
        "cm_crash_30d_fwd": {
          "tp": 0,
          "fp": 49,
          "fn": 0,
          "tn": 439,
          "precision": 0.0,
          "recall": null
        },
        "percentile": 0.9
      },
      {
        "threshold": 0.6916340411322182,
        "days": 488,
        "crisis_days": 39,
        "crisis_share": 0.07991803278688525,
        "base_dd_2m": 0.10860655737704918,
        "base_crash_1d_fwd": 0.0,
        "base_crash_30d_fwd": 0.0,
        "hit_dd_2m": 0.6410256410256411,
        "lift_dd_2m": 5.902273826802129,
        "cm_dd_2m": {
          "tp": 25,
          "fp": 14,
          "fn": 28,
          "tn": 421,
          "precision": 0.6410256410256411,
          "recall": 0.4716981132075472
        },
        "hit_crash_1d_fwd": 0.0,
        "lift_crash_1d_fwd": null,
        "cm_crash_1d_fwd": {
          "tp": 0,
          "fp": 39,
          "fn": 0,
          "tn": 449,
          "precision": 0.0,
          "recall": null
        },
        "hit_crash_30d_fwd": 0.0,
        "lift_crash_30d_fwd": null,
        "cm_crash_30d_fwd": {
          "tp": 0,
          "fp": 39,
          "fn": 0,
          "tn": 449,
          "precision": 0.0,
          "recall": null
        },
        "percentile": 0.92
      },
      {
        "threshold": 0.7182290156485782,
        "days": 488,
        "crisis_days": 30,
        "crisis_share": 0.06147540983606557,
        "base_dd_2m": 0.10860655737704918,
        "base_crash_1d_fwd": 0.0,
        "base_crash_30d_fwd": 0.0,
        "hit_dd_2m": 0.7333333333333333,
        "lift_dd_2m": 6.752201257861635,
        "cm_dd_2m": {
          "tp": 22,
          "fp": 8,
          "fn": 31,
          "tn": 427,
          "precision": 0.7333333333333333,
          "recall": 0.41509433962264153
        },
        "hit_crash_1d_fwd": 0.0,
        "lift_crash_1d_fwd": null,
        "cm_crash_1d_fwd": {
          "tp": 0,
          "fp": 30,
          "fn": 0,
          "tn": 458,
          "precision": 0.0,
          "recall": null
        },
        "hit_crash_30d_fwd": 0.0,
        "lift_crash_30d_fwd": null,
        "cm_crash_30d_fwd": {
          "tp": 0,
          "fp": 30,
          "fn": 0,
          "tn": 458,
          "precision": 0.0,
          "recall": null
        },
        "percentile": 0.94
      },
      {
        "threshold": 0.7618476971861982,
        "days": 488,
        "crisis_days": 20,
        "crisis_share": 0.040983606557377046,
        "base_dd_2m": 0.10860655737704918,
        "base_crash_1d_fwd": 0.0,
        "base_crash_30d_fwd": 0.0,
        "hit_dd_2m": 0.75,
        "lift_dd_2m": 6.905660377358491,
        "cm_dd_2m": {
          "tp": 15,
          "fp": 5,
          "fn": 38,
          "tn": 430,
          "precision": 0.75,
          "recall": 0.2830188679245283
        },
        "hit_crash_1d_fwd": 0.0,
        "lift_crash_1d_fwd": null,
        "cm_crash_1d_fwd": {
          "tp": 0,
          "fp": 20,
          "fn": 0,
          "tn": 468,
          "precision": 0.0,
          "recall": null
        },
        "hit_crash_30d_fwd": 0.0,
        "lift_crash_30d_fwd": null,
        "cm_crash_30d_fwd": {
          "tp": 0,
          "fp": 20,
          "fn": 0,
          "tn": 468,
          "precision": 0.0,
          "recall": null
        },
        "percentile": 0.96
      },
      {
        "threshold": 0.851083541546064,
        "days": 488,
        "crisis_days": 10,
        "crisis_share": 0.020491803278688523,
        "base_dd_2m": 0.10860655737704918,
        "base_crash_1d_fwd": 0.0,
        "base_crash_30d_fwd": 0.0,
        "hit_dd_2m": 0.9,
        "lift_dd_2m": 8.28679245283019,
        "cm_dd_2m": {
          "tp": 9,
          "fp": 1,
          "fn": 44,
          "tn": 434,
          "precision": 0.9,
          "recall": 0.16981132075471697
        },
        "hit_crash_1d_fwd": 0.0,
        "lift_crash_1d_fwd": null,
        "cm_crash_1d_fwd": {
          "tp": 0,
          "fp": 10,
          "fn": 0,
          "tn": 478,
          "precision": 0.0,
          "recall": null
        },
        "hit_crash_30d_fwd": 0.0,
        "lift_crash_30d_fwd": null,
        "cm_crash_30d_fwd": {
          "tp": 0,
          "fp": 10,
          "fn": 0,
          "tn": 478,
          "precision": 0.0,
          "recall": null
        },
        "percentile": 0.98
      }
    ]
  },
  "debug": {
    "latest_features": {
      "WEI": {
        "fred_id": "WEI",
        "raw_level": 2.7,
        "feature_value": -0.5300000000000002,
        "z": -1.0352115239785675,
        "stale": false,
        "last_obs_date": "2026-02-07",
        "stale_days": 12
      },
      "ICSA": {
        "fred_id": "ICSA",
        "raw_level": 227000.0,
        "feature_value": 0.02383497239351584,
        "z": 0.6487123105735989,
        "stale": false,
        "last_obs_date": "2026-02-07",
        "stale_days": 12
      },
      "CCSA": {
        "fred_id": "CCSA",
        "raw_level": 1862000.0,
        "feature_value": -0.0004043181230031223,
        "z": 0.5270231308262899,
        "stale": false,
        "last_obs_date": "2026-01-31",
        "stale_days": 19
      },
      "T10Y3M": {
        "fred_id": "T10Y3M",
        "raw_level": 0.39,
        "feature_value": -0.39,
        "z": -0.39916578403366665,
        "stale": false,
        "last_obs_date": "2026-02-18",
        "stale_days": 1
      },
      "HY_OAS": {
        "fred_id": "BAMLH0A0HYM2",
        "raw_level": 2.94,
        "feature_value": 3.19,
        "z": -0.44601968960225236,
        "stale": false,
        "last_obs_date": "2026-02-17",
        "stale_days": 2
      },
      "IG_OAS": {
        "fred_id": "BAMLC0A0CM",
        "raw_level": 0.8,
        "feature_value": 0.8600000000000001,
        "z": -0.7230948683309796,
        "stale": false,
        "last_obs_date": "2026-02-17",
        "stale_days": 2
      },
      "NFCI": {
        "fred_id": "NFCI",
        "raw_level": -0.56306,
        "feature_value": -0.56306,
        "z": -1.0113970151232061,
        "stale": false,
        "last_obs_date": "2026-02-06",
        "stale_days": 13
      },
      "STLFSI4": {
        "fred_id": "STLFSI4",
        "raw_level": -0.6208,
        "feature_value": -0.6208,
        "z": -0.38219885924692215,
        "stale": false,
        "last_obs_date": "2026-02-13",
        "stale_days": 6
      },
      "VIX": {
        "fred_id": "VIXCLS",
        "raw_level": 20.29,
        "feature_value": 20.29,
        "z": 0.2312367002159316,
        "stale": false,
        "last_obs_date": "2026-02-17",
        "stale_days": 2
      },
      "SP500": {
        "fred_id": "SP500",
        "raw_level": 6843.22,
        "feature_value": 0.006681044087003141,
        "z": 0.4734639661610346,
        "stale": false,
        "last_obs_date": "2026-02-17",
        "stale_days": 2
      },
      "SPX_RVOL_1M": {
        "fred_id": "DERIVED_FROM_FRED_OR_SP500",
        "raw_level": null,
        "feature_value": 0.007191029173667338,
        "z": -0.5012977561949854,
        "stale": false,
        "last_obs_date": "2026-02-17",
        "stale_days": 2
      },
      "SPX_MDD_1M": {
        "fred_id": "DERIVED_FROM_FRED_OR_SP500",
        "raw_level": null,
        "feature_value": 0.025821798068380586,
        "z": -0.6366429760519225,
        "stale": false,
        "last_obs_date": "2026-02-17",
        "stale_days": 2
      },
      "SPX_RET_5D_NEG": {
        "fred_id": "DERIVED_FROM_FRED_OR_SP500",
        "raw_level": null,
        "feature_value": -0.0015308601502175279,
        "z": 0.03125973194759039,
        "stale": false,
        "last_obs_date": "2026-02-17",
        "stale_days": 2
      },
      "SPX_RET_20D_NEG": {
        "fred_id": "DERIVED_FROM_FRED_OR_SP500",
        "raw_level": null,
        "feature_value": 0.010144141407566587,
        "z": 0.4726764991881832,
        "stale": false,
        "last_obs_date": "2026-02-17",
        "stale_days": 2
      },
      "VIX_CHG_5D_POS": {
        "fred_id": "DERIVED_FROM_FRED_OR_SP500",
        "raw_level": null,
        "feature_value": -0.5300000000000011,
        "z": -0.1581338592230887,
        "stale": false,
        "last_obs_date": "2026-02-17",
        "stale_days": 2
      },
      "HY_OAS_CHG_5D_POS": {
        "fred_id": "DERIVED_FROM_FRED_OR_SP500",
        "raw_level": null,
        "feature_value": 0.020000000000000018,
        "z": 0.10219716129353791,
        "stale": false,
        "last_obs_date": "2026-02-17",
        "stale_days": 2
      },
      "HY_OAS_CHG_20D_POS": {
        "fred_id": "DERIVED_FROM_FRED_OR_SP500",
        "raw_level": null,
        "feature_value": 0.2999999999999998,
        "z": 0.8076875586892361,
        "stale": false,
        "last_obs_date": "2026-02-17",
        "stale_days": 2
      },
      "IG_OAS_CHG_5D_POS": {
        "fred_id": "DERIVED_FROM_FRED_OR_SP500",
        "raw_level": null,
        "feature_value": 0.020000000000000018,
        "z": 0.41684595779729927,
        "stale": false,
        "last_obs_date": "2026-02-17",
        "stale_days": 2
      },
      "IG_OAS_CHG_20D_POS": {
        "fred_id": "DERIVED_FROM_FRED_OR_SP500",
        "raw_level": null,
        "feature_value": 0.07000000000000006,
        "z": 0.7086076111901813,
        "stale": false,
        "last_obs_date": "2026-02-17",
        "stale_days": 2
      },
      "HY_IG_SPREAD": {
        "fred_id": "DERIVED_FROM_FRED_OR_SP500",
        "raw_level": null,
        "feature_value": 2.1399999999999997,
        "z": -0.8018016437403771,
        "stale": false,
        "last_obs_date": "2026-02-17",
        "stale_days": 2
      },
      "HY_IG_CHG_20D_POS": {
        "fred_id": "DERIVED_FROM_FRED_OR_SP500",
        "raw_level": null,
        "feature_value": 0.22999999999999954,
        "z": 0.7714308298926498,
        "stale": false,
        "last_obs_date": "2026-02-17",
        "stale_days": 2
      },
      "NFCI_CHG_4W_POS": {
        "fred_id": "DERIVED_FROM_FRED_OR_SP500",
        "raw_level": null,
        "feature_value": 0.0009099999999999664,
        "z": -0.014362021096957193,
        "stale": false,
        "last_obs_date": "2026-02-17",
        "stale_days": 2
      },
      "STLFSI4_CHG_4W_POS": {
        "fred_id": "DERIVED_FROM_FRED_OR_SP500",
        "raw_level": null,
        "feature_value": 0.02949999999999997,
        "z": 0.08330106813387243,
        "stale": false,
        "last_obs_date": "2026-02-17",
        "stale_days": 2
      },
      "ICSA_CHG_4W_POS": {
        "fred_id": "DERIVED_FROM_FRED_OR_SP500",
        "raw_level": null,
        "feature_value": 17000.0,
        "z": 0.9044235167636664,
        "stale": false,
        "last_obs_date": "2026-02-17",
        "stale_days": 2
      },
      "CCSA_CHG_4W_POS": {
        "fred_id": "DERIVED_FROM_FRED_OR_SP500",
        "raw_level": null,
        "feature_value": 43000.0,
        "z": 0.6858853275642508,
        "stale": false,
        "last_obs_date": "2026-02-17",
        "stale_days": 2
      },
      "T10Y3M_CHG_20D_POS": {
        "fred_id": "DERIVED_FROM_FRED_OR_SP500",
        "raw_level": null,
        "feature_value": 0.16000000000000003,
        "z": 0.49896140626113766,
        "stale": false,
        "last_obs_date": "2026-02-17",
        "stale_days": 2
      }
    },
    "coef_abs_sorted": {
      "p_dd_2m": [
        {
          "feature": "NFCI",
          "coef": 0.23366945630474206
        },
        {
          "feature": "T10Y3M_CHG_20D_POS",
          "coef": 0.14271116608767084
        },
        {
          "feature": "IG_OAS",
          "coef": 0.139001386258499
        },
        {
          "feature": "CCSA_CHG_4W_POS",
          "coef": 0.13665017004076274
        },
        {
          "feature": "HY_OAS",
          "coef": 0.12806977298604297
        },
        {
          "feature": "HY_IG_SPREAD",
          "coef": 0.1247249372401339
        },
        {
          "feature": "SPX_RVOL_1M",
          "coef": 0.10552614028530859
        },
        {
          "feature": "VIX",
          "coef": 0.10167701307020302
        },
        {
          "feature": "T10Y3M",
          "coef": -0.08358247977710273
        },
        {
          "feature": "WEI",
          "coef": 0.08322140583417112
        },
        {
          "feature": "SPX_MDD_1M",
          "coef": 0.0775750562995502
        },
        {
          "feature": "NFCI_CHG_4W_POS",
          "coef": 0.07189433007867882
        },
        {
          "feature": "ICSA_CHG_4W_POS",
          "coef": -0.07164404896470798
        },
        {
          "feature": "CCSA",
          "coef": -0.06951764637183515
        },
        {
          "feature": "ICSA",
          "coef": -0.0621967380084465
        },
        {
          "feature": "STLFSI4",
          "coef": 0.05935546024254178
        },
        {
          "feature": "HY_IG_CHG_20D_POS",
          "coef": 0.052780361337741805
        },
        {
          "feature": "HY_OAS_CHG_20D_POS",
          "coef": 0.04837378445149293
        },
        {
          "feature": "SP500",
          "coef": 0.044411413339979035
        },
        {
          "feature": "IG_OAS_CHG_20D_POS",
          "coef": 0.03163540782157004
        }
      ],
      "p_crash_1d": [
        {
          "feature": "CCSA",
          "coef": 0.15670110338231394
        },
        {
          "feature": "T10Y3M_CHG_20D_POS",
          "coef": 0.12090529308444783
        },
        {
          "feature": "ICSA_CHG_4W_POS",
          "coef": -0.11939428759755781
        },
        {
          "feature": "HY_OAS_CHG_20D_POS",
          "coef": 0.10786093586925993
        },
        {
          "feature": "HY_IG_CHG_20D_POS",
          "coef": 0.10540777466514595
        },
        {
          "feature": "IG_OAS_CHG_5D_POS",
          "coef": 0.10321373914475623
        },
        {
          "feature": "NFCI_CHG_4W_POS",
          "coef": 0.10319202147922402
        },
        {
          "feature": "T10Y3M",
          "coef": 0.09452960088632574
        },
        {
          "feature": "IG_OAS_CHG_20D_POS",
          "coef": 0.09123885624533208
        },
        {
          "feature": "NFCI",
          "coef": -0.08962970748677554
        },
        {
          "feature": "VIX_CHG_5D_POS",
          "coef": 0.08875739739430596
        },
        {
          "feature": "HY_OAS_CHG_5D_POS",
          "coef": 0.08343124456522724
        },
        {
          "feature": "VIX",
          "coef": 0.05533325569126752
        },
        {
          "feature": "CCSA_CHG_4W_POS",
          "coef": -0.05525996246053585
        },
        {
          "feature": "SP500",
          "coef": -0.045420822392812726
        },
        {
          "feature": "SPX_MDD_1M",
          "coef": -0.03745906867325811
        },
        {
          "feature": "IG_OAS",
          "coef": -0.037342084503289824
        },
        {
          "feature": "STLFSI4",
          "coef": -0.03485629837169643
        },
        {
          "feature": "SPX_RVOL_1M",
          "coef": 0.03312049638973917
        },
        {
          "feature": "ICSA",
          "coef": -0.03166889260086355
        }
      ],
      "p_crash_30d": [
        {
          "feature": "NFCI",
          "coef": -0.20043518451292336
        },
        {
          "feature": "CCSA",
          "coef": 0.18498847180102884
        },
        {
          "feature": "CCSA_CHG_4W_POS",
          "coef": 0.13909891994444196
        },
        {
          "feature": "IG_OAS",
          "coef": -0.11526463675172884
        },
        {
          "feature": "SPX_MDD_1M",
          "coef": -0.10345836511687458
        },
        {
          "feature": "SP500",
          "coef": -0.09924399604774833
        },
        {
          "feature": "T10Y3M_CHG_20D_POS",
          "coef": 0.09376386137671007
        },
        {
          "feature": "T10Y3M",
          "coef": 0.0920946994998659
        },
        {
          "feature": "SPX_RVOL_1M",
          "coef": -0.07826270872358272
        },
        {
          "feature": "ICSA_CHG_4W_POS",
          "coef": -0.06340087368652607
        },
        {
          "feature": "ICSA",
          "coef": 0.058289837512100824
        },
        {
          "feature": "NFCI_CHG_4W_POS",
          "coef": 0.05790758092808613
        },
        {
          "feature": "VIX",
          "coef": -0.04917105830861921
        },
        {
          "feature": "HY_OAS",
          "coef": -0.04547584742865975
        },
        {
          "feature": "STLFSI4",
          "coef": -0.037021490673958185
        },
        {
          "feature": "SPX_RET_20D_NEG",
          "coef": -0.036206679949688
        },
        {
          "feature": "HY_IG_SPREAD",
          "coef": -0.03369948734796975
        },
        {
          "feature": "SPX_RET_5D_NEG",
          "coef": -0.027962862750933643
        },
        {
          "feature": "STLFSI4_CHG_4W_POS",
          "coef": -0.023481542038093155
        },
        {
          "feature": "WEI",
          "coef": 0.02346236547881257
        }
      ]
    },
    "feature_keys": [
      "WEI",
      "ICSA",
      "CCSA",
      "T10Y3M",
      "HY_OAS",
      "IG_OAS",
      "NFCI",
      "STLFSI4",
      "VIX",
      "SP500",
      "SPX_RVOL_1M",
      "SPX_MDD_1M",
      "SPX_RET_5D_NEG",
      "SPX_RET_20D_NEG",
      "VIX_CHG_5D_POS",
      "HY_OAS_CHG_5D_POS",
      "HY_OAS_CHG_20D_POS",
      "IG_OAS_CHG_5D_POS",
      "IG_OAS_CHG_20D_POS",
      "HY_IG_SPREAD",
      "HY_IG_CHG_20D_POS",
      "NFCI_CHG_4W_POS",
      "STLFSI4_CHG_4W_POS",
      "ICSA_CHG_4W_POS",
      "CCSA_CHG_4W_POS",
      "T10Y3M_CHG_20D_POS"
    ]
  }
}